platon_aide/__init__.py
platon_aide/calculator.py
platon_aide/contract.py
platon_aide/delegate.py
platon_aide/economic.py
platon_aide/govern.py
platon_aide/graphqls.py
platon_aide/main.py
platon_aide/restricting.py
platon_aide/slashing.py
platon_aide/staking.py
platon_aide/transfer.py
platon_aide/base/__init__.py
platon_aide/base/module.py
platon_aide/utils/__init__.py
platon_aide/utils/utils.py
platon_aide-2.0.1.dist-info/LICENSE
platon_aide-2.0.1.dist-info/METADATA
platon_aide-2.0.1.dist-info/WHEEL
platon_aide-2.0.1.dist-info/top_level.txt
platon_aide-2.0.1.dist-info/RECORD
