Metadata-Version: 2.1
Name: platon-aide
Version: 2.0.1
Summary: An aide that helps you quickly access the platon chain and use its basic functions.
Home-page: https://github.com/PlatONnetwork/platon-aide
Author: ssdut.steven
Author-email: ssdut.steven@gmail.com
License: MIT
Keywords: platon
Classifier: Development Status :: 4 - Beta
Classifier: Intended Audience :: Developers
Classifier: License :: OSI Approved :: MIT License
Classifier: Natural Language :: English
Classifier: Programming Language :: Python :: 3
Classifier: Programming Language :: Python :: 3.6
Classifier: Programming Language :: Python :: 3.7
Classifier: Programming Language :: Python :: 3.8
Classifier: Programming Language :: Python :: 3.9
License-File: LICENSE
Requires-Dist: web3 (>=5.23.0)
Requires-Dist: eth-account (>=0.5.9)
Requires-Dist: eth-hash (>=0.3.2)
Requires-Dist: eth-keys (>=0.3.4)
Requires-Dist: eth-typing (>=2.3.0)
Requires-Dist: eth-utils (>=1.10.0)
Requires-Dist: rlp (>=1.2.0)
Requires-Dist: gql (>=3.0.0rc0)
Provides-Extra: platon-aide
Requires-Dist: web3 (>=5.23.0) ; extra == 'platon-aide'
Requires-Dist: eth-account (>=0.5.9) ; extra == 'platon-aide'
Requires-Dist: eth-hash (>=0.3.2) ; extra == 'platon-aide'
Requires-Dist: eth-keys (>=0.3.4) ; extra == 'platon-aide'
Requires-Dist: eth-typing (>=2.3.0) ; extra == 'platon-aide'
Requires-Dist: eth-utils (>=1.10.0) ; extra == 'platon-aide'
Requires-Dist: rlp (>=1.2.0) ; extra == 'platon-aide'
Requires-Dist: gql (>=3.0.0rc0) ; extra == 'platon-aide'
